{
    "year": "1749",
    "month": "02",
    "day": "19",
    "title": "NO.XXXII. The Continuation of the Adventures of Roderick Random",
    "newspaper": "sussex-advertiser",
    "summary": "Part 32 of the adventures of Roderick Random. The narrator listens to a companion's harrowing account of falling into desperate street prostitution and illness after a failed inheritance scam. Moved by her tragic transformation from a wealthy upbringing to extreme poverty, the narrator helps nursing her back to health while they plot an escape from their circumstances.",
    "source_url": "https://www.britishnewspaperarchive.co.uk/viewer/bl/0000260/17490219/001/0001"
}